mqttwrappr/__init__.py
mqttwrappr/mqtt_client.py
mqttwrappr-0.0.11.dist-info/licenses/LICENSE
mqttwrappr-0.0.11.dist-info/METADATA
mqttwrappr-0.0.11.dist-info/WHEEL
mqttwrappr-0.0.11.dist-info/top_level.txt
mqttwrappr-0.0.11.dist-info/RECORD
