Metadata-Version: 2.4
Name: mqttwrappr
Version: 0.0.11
Summary: A user friendly wrappr for easy mqtt operations
Author-email: Nils Klasen <likeable.versed-78@icloud.com>
License-Expression: MIT
Project-URL: Homepage, https://git-ce.rwth-aachen.de/kls/mqttwrappr
Project-URL: Documentation, https://mqttwrappr-dee8f6.pages.git-ce.rwth-aachen.de
Project-URL: Issues, https://git-ce.rwth-aachen.de/kls/mqttwrappr/-/issues
Classifier: Programming Language :: Python :: 3.9
Classifier: Programming Language :: Python :: 3.10
Classifier: Programming Language :: Python :: 3.11
Classifier: Programming Language :: Python :: 3.12
Classifier: Operating System :: OS Independent
Requires-Python: <4,>=3.9
License-File: LICENSE
Requires-Dist: paho-mqtt==1.6.1
Requires-Dist: pyyaml
Dynamic: license-file
